waifutagger/__init__.py
waifutagger/constants.py
waifutagger/core.py
waifutagger/formatters.py
waifutagger/utils.py
waifutagger/version.py
waifutagger-0.1.1.dist-info/METADATA
waifutagger-0.1.1.dist-info/WHEEL
waifutagger-0.1.1.dist-info/top_level.txt
waifutagger-0.1.1.dist-info/RECORD
