Metadata-Version: 2.1
Name: waifutagger
Version: 0.1.1
Summary: A simple tagger for anime-style images using SmilingWolf models
Author-email: arielfikrua <arielfikrua@gmail.com>
Requires-Python: >=3.7
Requires-Dist: numpy>=1.19.0
Requires-Dist: onnxruntime>=1.7.0
Requires-Dist: Pillow>=8.0.0
Requires-Dist: huggingface-hub>=0.7.0
Requires-Dist: pandas>=1.2.0
